integrate/__init__.py
integrate/connect.py
integrate/data.py
integrate/orders.py
integrate/py.typed
integrate/ws.py
pyintegrate-1.2.0.dist-info/LICENSE
pyintegrate-1.2.0.dist-info/METADATA
pyintegrate-1.2.0.dist-info/WHEEL
pyintegrate-1.2.0.dist-info/RECORD
