Metadata-Version: 2.3
Name: pyintegrate
Version: 1.2.0
Summary: Definedge Securities Integrate API Python Client
License: MIT
Author: Definedge Securities
Author-email: integrate@definedge.com
Requires-Python: >=3.9,<4.0
Classifier: Development Status :: 5 - Production/Stable
Classifier: Intended Audience :: Developers
Classifier: Intended Audience :: Financial and Insurance Industry
Classifier: License :: OSI Approved :: MIT License
Classifier: Natural Language :: English
Classifier: Programming Language :: Python
Classifier: Programming Language :: Python :: 3
Classifier: Programming Language :: Python :: 3.9
Classifier: Programming Language :: Python :: 3.10
Classifier: Programming Language :: Python :: 3.11
Classifier: Programming Language :: Python :: 3.12
Classifier: Programming Language :: Python :: 3.13
Classifier: Topic :: Office/Business :: Financial :: Investment
Classifier: Topic :: Software Development :: Libraries
Classifier: Topic :: Software Development :: Libraries :: Python Modules
Requires-Dist: autobahn (>=23.6.2,<24.0.0)
Requires-Dist: pyopenssl (>=23.2.0,<24.0.0)
Requires-Dist: requests (>=2.31.0,<3.0.0)
Requires-Dist: service-identity (>=23.1.0,<24.0.0)
Requires-Dist: twisted (>=22.10.0,<23.0.0)
Project-URL: Documentation, https://pyintegrate.readthedocs.io/en/latest/
Project-URL: Homepage, https://www.definedgesecurities.com/api-documentation/
Project-URL: Repository, https://github.com/Definedge-Securities/pyintegrate
